{
    "works": [
        {
            "name": "Micalet App",
            "date": 2021,
            "description": "Project done for a studio that wanted to bring the experience of visiting a museum to a mobile application. \n\nIt consists of the main app developed with Flutter to offer a cross-platform experience. And a web so that the studio members can easily add data points to the app. In the back we have a noSQL database powered by firebase.",
            "link": "https://twitter.com/InfoMicalet?s=20",
            "demo": "demo_micalet.gif",
            "tags": ["flutter", "vue", "firebase","front-end", "back-end", "dart"]
        },
        {
            "name": "This portfolio",
            "date": "2020",
            "description": "This single-page app, developed with vue.js and taking special care about the design.",
            "tags": [
                "front-end",
                "vue",
                "ui"
            ],
            "link": "http://github.com/qiqetes/qiqetes-portfolio",
            "live": "https://qiqetes.github.io/qiqetes-portfolio"
        },
        {
            "name": "My perillin Noise",
            "date": "2020",
            "description": "My approach to creating pseudo-random noise images. Originally it was an approach to create procedural terrains for unity. Written in c# with threading optimizations.",
            "tags": [
                "algorithms",
                "c#"
            ],
            "link": "http://github.com/qiqetes/qiqetes-portfolio"
        },
        {
            "name": "Markov Chain Twitter",
            "date": "2020",
            "description": "With machine learning it learns from user tweets and publish random tweets with the leanguage learnt.",
            "tags": [
                "algorithms",
                "machine learning",
                "python"
            ],
            "link": "https://github.com/qiqetes/Tweet-generator_ML"
        },
        {
            "name": "Cubolores (GameJam UPV)",
            "date": "2019",
            "description": "Winner game developed in a jam of 34 hours for the Polytechnic University of Valencia. We used unity as engine and blender 3D to make the assets. A video will be available soon.",
            "tags": [
                "gamedev",
                "unity",
                "c#",
                "blender"
            ],
            "link": "https://ragnarokshadows.itch.io/cubelores?secret=PsaU8wtR0liDJk7YfSdYpJ6mgNA"
        },
        {
            "name": "Cards Against Humanity",
            "date": "2019-2020",
            "description": "My most ambitious project. It is a mobile multiplayer game developed for IOs and android. It will be launched this summer.",
            "tags": [
                "front-end",
                "flutter",
                "dart",
                "ui"
            ],
            "demo":"demo_cah.gif"
        },
        {
            "name": "My web diary",
            "date": "2018",
            "description": "Unfinished project, where I tried to make a personal diary application using Vue",
            "tags": [
                "front-end",
                "react",
                "node.js",
                "ui"
            ],
            "link": "https://github.com/qiqetes/My-diary-webapp"
        },
        {
            "name": "Todo-list app",
            "description": "Single-page application developing the typical to-do list.",
            "date": "2018",
            "tags": [
                "front-end",
                "react"
            ],
            "link": "http://github.com/qiqetes/qiqetes-portfolio"
        }
    ],
    "skills": [
        {
            "name": "Front-end",
            "subskills": [
                "vue.js",
                "flutter",
                "React",
                "vuex",
                "bootstrap",
                "sass/scss",
                "html5 + css"
            ]
        },
        {
            "name": "Back-end",
            "subskills": [
                "c# .Net",
                "python",
                "java",
                "firebase",
                "node.js"
            ]
        },
        {
            "name": "Gamedev",
            "subskills": [
                "Unity",
                "Blender",
                "Godot",
                "3Ds Max"
            ]
        },
        {
            "name": "Design +",
            "subskills": [
                "Photoshop",
                "Adobe XD",
                "Illustrator",
                "After Effects",
                "Git"
            ]
        }
    ],
    "resumeLink": "https://drive.google.com/file/d/1z4Xo-qju8CZ9PtrNgvqZaLFUDmyOedcN/view"
}